[
  {
    "id": "11515130-2024-06",
    "date": "2024-05-11",
    "batter": {
      "jaBoxscoreName": "岡本和",
      "playerId": "11515130",
      "boxscoreName": "K.Okamoto",
      "batSide": "R",
      "teamCode": "G",
      "primaryNumber": "25",
      "jaRegisteredName": "岡本　和真",
      "fullLFMName": "Okamoto, Kazuma"
    },
    "pitcher": {
      "jaBoxscoreName": "小川",
      "boxscoreName": "Ogawa",
      "pitchHand": "R",
      "teamCode": "S",
      "primaryNumber": "29",
      "jaRegisteredName": "小川　泰弘",
      "fullLFMName": "Ogawa, Yasuhiro"
    },
    "number": 6,
    "inning": 2,
    "halfInning": "top",
    "outs": 0,
    "RoB": "---",
    "count": {
      "balls": 2,
      "strikes": 0
    },
    "runs": {
      "road": 0,
      "home": 1
    },
    "bop": 4,
    "rbi": 1,
    "whereHit": "78",
    "venue": {
      "jaBoxscoreName": "神宮",
      "boxscoreName": "Jingu",
      "jaName": "神宮",
      "name": "Jingu Stadium"
    },
    "teams": {
      "road": {
        "teamCode": "G",
        "teamName": "Giants",
        "score": 4
      },
      "home": {
        "teamCode": "S",
        "teamName": "Swallows",
        "score": 3
      }
    },
    "jaText": "左中間ソロホームラン（打点1）",
    "text": "K.Okamoto homers (6) to left center.",
    "url": "https://npb.jp/scores/2024/0511/s-g-07/playbyplay.html#com2-1"
  },
  {
    "id": "11515130-2024-07",
    "date": "2024-05-11",
    "batter": {
      "jaBoxscoreName": "岡本和",
      "playerId": "11515130",
      "boxscoreName": "K.Okamoto",
      "batSide": "R",
      "teamCode": "G",
      "primaryNumber": "25",
      "jaRegisteredName": "岡本　和真",
      "fullLFMName": "Okamoto, Kazuma"
    },
    "pitcher": {
      "jaBoxscoreName": "小川",
      "boxscoreName": "Ogawa",
      "pitchHand": "R",
      "teamCode": "S",
      "primaryNumber": "29",
      "jaRegisteredName": "小川　泰弘",
      "fullLFMName": "Ogawa, Yasuhiro"
    },
    "number": 7,
    "inning": 4,
    "halfInning": "top",
    "outs": 1,
    "RoB": "1--",
    "count": {
      "balls": 1,
      "strikes": 2
    },
    "runs": {
      "road": 1,
      "home": 1
    },
    "bop": 4,
    "rbi": 2,
    "whereHit": "78",
    "venue": {
      "jaBoxscoreName": "神宮",
      "boxscoreName": "Jingu",
      "jaName": "神宮",
      "name": "Jingu Stadium"
    },
    "teams": {
      "road": {
        "teamCode": "G",
        "teamName": "Giants",
        "score": 4
      },
      "home": {
        "teamCode": "S",
        "teamName": "Swallows",
        "score": 3
      }
    },
    "jaText": "左中間2ランホームラン（打点2）",
    "text": "K.Okamoto homers (7) to left center.",
    "url": "https://npb.jp/scores/2024/0511/s-g-07/playbyplay.html#com4-1"
  },
  {
    "id": "51455151-2024-02",
    "date": "2024-05-11",
    "batter": {
      "jaBoxscoreName": "長岡",
      "playerId": "51455151",
      "boxscoreName": "Nagaoka",
      "batSide": "L",
      "teamCode": "S",
      "primaryNumber": "7",
      "jaRegisteredName": "長岡　秀樹",
      "fullLFMName": "Nagaoka, Hideki"
    },
    "pitcher": {
      "jaBoxscoreName": "菅野",
      "boxscoreName": "Sugano",
      "pitchHand": "R",
      "teamCode": "G",
      "primaryNumber": "18",
      "jaRegisteredName": "菅野　智之",
      "fullLFMName": "Sugano, Tomoyuki"
    },
    "number": 2,
    "inning": 4,
    "halfInning": "bottom",
    "outs": 2,
    "RoB": "---",
    "count": {
      "balls": 1,
      "strikes": 0
    },
    "runs": {
      "road": 4,
      "home": 1
    },
    "bop": 6,
    "rbi": 1,
    "whereHit": "9",
    "venue": {
      "jaBoxscoreName": "神宮",
      "boxscoreName": "Jingu",
      "jaName": "神宮",
      "name": "Jingu Stadium"
    },
    "teams": {
      "road": {
        "teamCode": "G",
        "teamName": "Giants",
        "score": 4
      },
      "home": {
        "teamCode": "S",
        "teamName": "Swallows",
        "score": 3
      }
    },
    "jaText": "ライトソロホームラン（打点1）",
    "text": "Nagaoka homers (2) to right field.",
    "url": "https://npb.jp/scores/2024/0511/s-g-07/playbyplay.html#com4-2"
  },
  {
    "id": "71075138-2024-06",
    "date": "2024-05-11",
    "batter": {
      "jaBoxscoreName": "近本",
      "playerId": "71075138",
      "boxscoreName": "Chikamoto",
      "batSide": "L",
      "teamCode": "T",
      "primaryNumber": "5",
      "jaRegisteredName": "近本　光司",
      "fullLFMName": "Chikamoto, Koji"
    },
    "pitcher": {
      "jaBoxscoreName": "中川颯",
      "boxscoreName": "H.Nakagawa",
      "pitchHand": "R",
      "teamCode": "DB",
      "primaryNumber": "53",
      "jaRegisteredName": "中川　颯",
      "fullLFMName": "Nakagawa, Hayate"
    },
    "number": 6,
    "inning": 3,
    "halfInning": "top",
    "outs": 2,
    "RoB": "123",
    "count": {
      "balls": 3,
      "strikes": 2
    },
    "runs": {
      "road": 5,
      "home": 2
    },
    "bop": 1,
    "rbi": 4,
    "whereHit": "9",
    "venue": {
      "jaBoxscoreName": "横浜",
      "boxscoreName": "Yokohama",
      "jaName": "横浜スタジアム",
      "name": "Yokohama Stadium"
    },
    "teams": {
      "road": {
        "teamCode": "T",
        "teamName": "Tigers",
        "score": 9
      },
      "home": {
        "teamCode": "DB",
        "teamName": "Baystars",
        "score": 11
      }
    },
    "jaText": "ライト満塁ホームラン（打点4）",
    "text": "Chikamoto homers (6) to right field.",
    "url": "https://npb.jp/scores/2024/0511/db-t-07/playbyplay.html#com3-1"
  },
  {
    "id": "51555151-2024-01",
    "date": "2024-05-11",
    "batter": {
      "jaBoxscoreName": "蝦名",
      "playerId": "51555151",
      "boxscoreName": "Ebina",
      "batSide": "R",
      "teamCode": "DB",
      "primaryNumber": "61",
      "jaRegisteredName": "蝦名　達夫",
      "fullLFMName": "Ebina, Tatsuo"
    },
    "pitcher": {
      "jaBoxscoreName": "岩崎",
      "boxscoreName": "Iwazaki",
      "pitchHand": "L",
      "teamCode": "T",
      "primaryNumber": "13",
      "jaRegisteredName": "岩崎　優",
      "fullLFMName": "Iwazaki, Suguru"
    },
    "number": 1,
    "inning": 8,
    "halfInning": "bottom",
    "outs": 1,
    "RoB": "1--",
    "count": {
      "balls": 2,
      "strikes": 1
    },
    "runs": {
      "road": 9,
      "home": 7
    },
    "bop": 1,
    "rbi": 2,
    "whereHit": "8",
    "venue": {
      "jaBoxscoreName": "横浜",
      "boxscoreName": "Yokohama",
      "jaName": "横浜スタジアム",
      "name": "Yokohama Stadium"
    },
    "teams": {
      "road": {
        "teamCode": "T",
        "teamName": "Tigers",
        "score": 9
      },
      "home": {
        "teamCode": "DB",
        "teamName": "Baystars",
        "score": 11
      }
    },
    "jaText": "センター2ランホームラン（打点2）",
    "text": "Ebina homers (1) to center field.",
    "url": "https://npb.jp/scores/2024/0511/db-t-07/playbyplay.html#com8-2"
  },
  {
    "id": "41945131-2024-02",
    "date": "2024-05-11",
    "batter": {
      "jaBoxscoreName": "筒香",
      "playerId": "41945131",
      "boxscoreName": "Tsutsugo",
      "batSide": "L",
      "teamCode": "DB",
      "primaryNumber": "25",
      "jaRegisteredName": "筒香　嘉智",
      "fullLFMName": "Tsutsugo, Yoshitomo"
    },
    "pitcher": {
      "jaBoxscoreName": "岩崎",
      "boxscoreName": "Iwazaki",
      "pitchHand": "L",
      "teamCode": "T",
      "primaryNumber": "13",
      "jaRegisteredName": "岩崎　優",
      "fullLFMName": "Iwazaki, Suguru"
    },
    "number": 2,
    "inning": 8,
    "halfInning": "bottom",
    "outs": 2,
    "RoB": "---",
    "count": {
      "balls": 0,
      "strikes": 2
    },
    "runs": {
      "road": 9,
      "home": 9
    },
    "bop": 3,
    "rbi": 1,
    "whereHit": "9",
    "venue": {
      "jaBoxscoreName": "横浜",
      "boxscoreName": "Yokohama",
      "jaName": "横浜スタジアム",
      "name": "Yokohama Stadium"
    },
    "teams": {
      "road": {
        "teamCode": "T",
        "teamName": "Tigers",
        "score": 9
      },
      "home": {
        "teamCode": "DB",
        "teamName": "Baystars",
        "score": 11
      }
    },
    "jaText": "ライトソロホームラン（打点1）",
    "text": "Tsutsugo homers (2) to right field.",
    "url": "https://npb.jp/scores/2024/0511/db-t-07/playbyplay.html#com8-2"
  },
  {
    "id": "13115153-2024-05",
    "date": "2024-05-11",
    "batter": {
      "jaBoxscoreName": "牧",
      "playerId": "13115153",
      "boxscoreName": "Maki",
      "batSide": "R",
      "teamCode": "DB",
      "primaryNumber": "2",
      "jaRegisteredName": "牧　秀悟",
      "fullLFMName": "Maki, Shugo"
    },
    "pitcher": {
      "jaBoxscoreName": "岡留",
      "boxscoreName": "Okadome",
      "pitchHand": "R",
      "teamCode": "T",
      "primaryNumber": "64",
      "jaRegisteredName": "岡留　英貴",
      "fullLFMName": "Okadome, Hidetaka"
    },
    "number": 5,
    "inning": 8,
    "halfInning": "bottom",
    "outs": 2,
    "RoB": "---",
    "count": {
      "balls": 3,
      "strikes": 2
    },
    "runs": {
      "road": 9,
      "home": 10
    },
    "bop": 4,
    "rbi": 1,
    "whereHit": "7",
    "venue": {
      "jaBoxscoreName": "横浜",
      "boxscoreName": "Yokohama",
      "jaName": "横浜スタジアム",
      "name": "Yokohama Stadium"
    },
    "teams": {
      "road": {
        "teamCode": "T",
        "teamName": "Tigers",
        "score": 9
      },
      "home": {
        "teamCode": "DB",
        "teamName": "Baystars",
        "score": 11
      }
    },
    "jaText": "レフトソロホームラン（打点1）",
    "text": "Maki homers (5) to left field.",
    "url": "https://npb.jp/scores/2024/0511/db-t-07/playbyplay.html#com8-2"
  }
]