[
  {
    "date": "2024-08-08",
    "runner": {
      "playerId": "31135133",
      "jaRegisteredName": "秋山　翔吾",
      "teamCode": "C",
      "primaryNumber": "9",
      "primaryPosition": "Outfielder",
      "jaStatus": "支配下選手",
      "batSide": "L",
      "pitchHand": "R",
      "height": "184",
      "weight": "86",
      "birthDate": "1988-04-16",
      "jaNotes": "",
      "notes": "",
      "jaBoxscoreName": "秋山",
      "boxscoreName": "Akiyama",
      "jaFullName": "秋山　翔吾",
      "jaFirstName": "翔吾",
      "jaLastName": "秋山",
      "fullLFMName": "Akiyama, Shogo",
      "firstName": "Shogo",
      "lastName": "Akiyama"
    },
    "batter": {
      "playerId": "93395153",
      "jaRegisteredName": "矢野　雅哉",
      "teamCode": "C",
      "primaryNumber": "61",
      "primaryPosition": "Infielder",
      "jaStatus": "支配下選手",
      "batSide": "L",
      "pitchHand": "R",
      "height": "171",
      "weight": "71",
      "birthDate": "1998-12-16",
      "jaNotes": "",
      "notes": "",
      "jaBoxscoreName": "矢野",
      "boxscoreName": "Yano",
      "jaFullName": "矢野　雅哉",
      "jaFirstName": "雅哉",
      "jaLastName": "矢野",
      "fullLFMName": "Yano, Masaya",
      "firstName": "Masaya",
      "lastName": "Yano"
    },
    "pitcher": {
      "playerId": "41045138",
      "jaRegisteredName": "戸郷　翔征",
      "teamCode": "G",
      "primaryNumber": "20",
      "primaryPosition": "Pitcher",
      "jaStatus": "支配下選手",
      "batSide": "R",
      "pitchHand": "R",
      "height": "187",
      "weight": "84",
      "birthDate": "2000-04-04",
      "jaNotes": "",
      "notes": "",
      "jaBoxscoreName": "戸郷",
      "boxscoreName": "Togo",
      "jaFullName": "戸郷　翔征",
      "jaFirstName": "翔征",
      "jaLastName": "戸郷",
      "fullLFMName": "Togo, Shosei",
      "firstName": "Shosei",
      "lastName": "Togo"
    },
    "catcher": {
      "playerId": "21325136",
      "jaRegisteredName": "大城　卓三",
      "teamCode": "G",
      "primaryNumber": "24",
      "primaryPosition": "Catcher",
      "jaStatus": "支配下選手",
      "batSide": "L",
      "pitchHand": "R",
      "height": "187",
      "weight": "90",
      "birthDate": "1993-02-11",
      "jaNotes": "",
      "notes": "",
      "jaBoxscoreName": "大城卓",
      "boxscoreName": "T.Ohshiro",
      "jaFullName": "大城　卓三",
      "jaFirstName": "卓三",
      "jaLastName": "大城",
      "fullLFMName": "Ohshiro, Takumi",
      "firstName": "Takumi",
      "lastName": "Ohshiro"
    },
    "scoring": "CaughtStealing",
    "base": "2B",
    "pickoff": "",
    "inning": 3,
    "halfInning": "top",
    "outs": 1,
    "RoB": "1--",
    "runs": {
      "road": 0,
      "home": 0
    },
    "venue": {
      "jaBoxscoreName": "東京ドーム",
      "boxscoreName": "Tokyo Dome",
      "jaName": "東京ドーム",
      "name": "Tokyo Dome"
    },
    "teams": {
      "road": {
        "teamCode": "C",
        "teamName": "Carp",
        "score": 0
      },
      "home": {
        "teamCode": "G",
        "teamName": "Giants",
        "score": 5
      }
    },
    "jaText": "（走者・秋山）二塁盗塁失敗",
    "text": "Akiyama caught stealing 2nd base.",
    "url": "https://npb.jp/scores/2024/0808/g-c-16/playbyplay.html#com3-1",
    "catchers": [
      {
        "playerId": "21325136",
        "jaRegisteredName": "大城　卓三",
        "teamCode": "G",
        "primaryNumber": "24",
        "primaryPosition": "Catcher",
        "jaStatus": "支配下選手",
        "batSide": "L",
        "pitchHand": "R",
        "height": "187",
        "weight": "90",
        "birthDate": "1993-02-11",
        "jaNotes": "",
        "notes": "",
        "jaBoxscoreName": "大城卓",
        "boxscoreName": "T.Ohshiro",
        "jaFullName": "大城　卓三",
        "jaFirstName": "卓三",
        "jaLastName": "大城",
        "fullLFMName": "Ohshiro, Takumi",
        "firstName": "Takumi",
        "lastName": "Ohshiro"
      }
    ]
  },
  {
    "date": "2024-08-08",
    "runner": {
      "playerId": "11915134",
      "jaRegisteredName": "坂倉　将吾",
      "teamCode": "C",
      "primaryNumber": "31",
      "primaryPosition": "Catcher",
      "jaStatus": "支配下選手",
      "batSide": "L",
      "pitchHand": "R",
      "height": "177",
      "weight": "89",
      "birthDate": "1998-05-29",
      "jaNotes": "",
      "notes": "",
      "jaBoxscoreName": "坂倉",
      "boxscoreName": "Sakakura",
      "jaFullName": "坂倉　将吾",
      "jaFirstName": "将吾",
      "jaLastName": "坂倉",
      "fullLFMName": "Sakakura, Shogo",
      "firstName": "Shogo",
      "lastName": "Sakakura"
    },
    "batter": {
      "playerId": "51055155",
      "jaRegisteredName": "末包　昇大",
      "teamCode": "C",
      "primaryNumber": "52",
      "primaryPosition": "Outfielder",
      "jaStatus": "支配下選手",
      "batSide": "R",
      "pitchHand": "R",
      "height": "188",
      "weight": "112",
      "birthDate": "1996-05-27",
      "jaNotes": "",
      "notes": "",
      "jaBoxscoreName": "末包",
      "boxscoreName": "Suekane",
      "jaFullName": "末包　昇大",
      "jaFirstName": "昇大",
      "jaLastName": "末包",
      "fullLFMName": "Suekane, Shota",
      "firstName": "Shota",
      "lastName": "Suekane"
    },
    "pitcher": {
      "playerId": "41045138",
      "jaRegisteredName": "戸郷　翔征",
      "teamCode": "G",
      "primaryNumber": "20",
      "primaryPosition": "Pitcher",
      "jaStatus": "支配下選手",
      "batSide": "R",
      "pitchHand": "R",
      "height": "187",
      "weight": "84",
      "birthDate": "2000-04-04",
      "jaNotes": "",
      "notes": "",
      "jaBoxscoreName": "戸郷",
      "boxscoreName": "Togo",
      "jaFullName": "戸郷　翔征",
      "jaFirstName": "翔征",
      "jaLastName": "戸郷",
      "fullLFMName": "Togo, Shosei",
      "firstName": "Shosei",
      "lastName": "Togo"
    },
    "catcher": {
      "playerId": "21325136",
      "jaRegisteredName": "大城　卓三",
      "teamCode": "G",
      "primaryNumber": "24",
      "primaryPosition": "Catcher",
      "jaStatus": "支配下選手",
      "batSide": "L",
      "pitchHand": "R",
      "height": "187",
      "weight": "90",
      "birthDate": "1993-02-11",
      "jaNotes": "",
      "notes": "",
      "jaBoxscoreName": "大城卓",
      "boxscoreName": "T.Ohshiro",
      "jaFullName": "大城　卓三",
      "jaFirstName": "卓三",
      "jaLastName": "大城",
      "fullLFMName": "Ohshiro, Takumi",
      "firstName": "Takumi",
      "lastName": "Ohshiro"
    },
    "scoring": "CaughtStealing",
    "base": "2B",
    "pickoff": "",
    "inning": 7,
    "halfInning": "top",
    "outs": 1,
    "RoB": "1--",
    "runs": {
      "road": 0,
      "home": 0
    },
    "venue": {
      "jaBoxscoreName": "東京ドーム",
      "boxscoreName": "Tokyo Dome",
      "jaName": "東京ドーム",
      "name": "Tokyo Dome"
    },
    "teams": {
      "road": {
        "teamCode": "C",
        "teamName": "Carp",
        "score": 0
      },
      "home": {
        "teamCode": "G",
        "teamName": "Giants",
        "score": 5
      }
    },
    "jaText": "（走者・坂倉）二塁盗塁失敗",
    "text": "Sakakura caught stealing 2nd base.",
    "url": "https://npb.jp/scores/2024/0808/g-c-16/playbyplay.html#com7-1",
    "catchers": [
      {
        "playerId": "21325136",
        "jaRegisteredName": "大城　卓三",
        "teamCode": "G",
        "primaryNumber": "24",
        "primaryPosition": "Catcher",
        "jaStatus": "支配下選手",
        "batSide": "L",
        "pitchHand": "R",
        "height": "187",
        "weight": "90",
        "birthDate": "1993-02-11",
        "jaNotes": "",
        "notes": "",
        "jaBoxscoreName": "大城卓",
        "boxscoreName": "T.Ohshiro",
        "jaFullName": "大城　卓三",
        "jaFirstName": "卓三",
        "jaLastName": "大城",
        "fullLFMName": "Ohshiro, Takumi",
        "firstName": "Takumi",
        "lastName": "Ohshiro"
      }
    ]
  },
  {
    "date": "2024-08-08",
    "runner": {
      "playerId": "21225133",
      "jaRegisteredName": "西川　遥輝",
      "teamCode": "S",
      "primaryNumber": "3",
      "primaryPosition": "Outfielder",
      "jaStatus": "支配下選手",
      "batSide": "L",
      "pitchHand": "R",
      "height": "181",
      "weight": "82",
      "birthDate": "1992-04-16",
      "jaNotes": "",
      "notes": "",
      "jaBoxscoreName": "西川",
      "boxscoreName": "Nishikawa",
      "jaFullName": "西川　遥輝",
      "jaFirstName": "遥輝",
      "jaLastName": "西川",
      "fullLFMName": "Nishikawa, Haruki",
      "firstName": "Haruki",
      "lastName": "Nishikawa"
    },
    "batter": {
      "playerId": "51355155",
      "jaRegisteredName": "岩田　幸宏",
      "teamCode": "S",
      "primaryNumber": "64",
      "primaryPosition": "Outfielder",
      "jaStatus": "支配下選手",
      "batSide": "L",
      "pitchHand": "L",
      "height": "175",
      "weight": "79",
      "birthDate": "1997-07-31",
      "jaNotes": "3/31 育成選手から支配下選手へ移行",
      "notes": "Registered(developmental player ->) (Mar. 31).",
      "jaBoxscoreName": "岩田",
      "boxscoreName": "Iwata",
      "jaFullName": "岩田　幸宏",
      "jaFirstName": "幸宏",
      "jaLastName": "岩田",
      "fullLFMName": "Iwata, Yukihiro",
      "firstName": "Yukihiro",
      "lastName": "Iwata"
    },
    "pitcher": {
      "playerId": "03905157",
      "jaRegisteredName": "Ｊ．ビーズリー",
      "teamCode": "T",
      "primaryNumber": "99",
      "primaryPosition": "Pitcher",
      "jaStatus": "支配下選手",
      "batSide": "R",
      "pitchHand": "R",
      "height": "191",
      "weight": "109",
      "birthDate": "1995-11-20",
      "jaNotes": "",
      "notes": "",
      "jaBoxscoreName": "ビーズリー",
      "boxscoreName": "Beasley",
      "jaFullName": "ジェレミー・ビーズリー",
      "jaFirstName": "ジェレミー",
      "jaLastName": "ビーズリー",
      "fullLFMName": "Beasley, Jeremy",
      "firstName": "Jeremy",
      "lastName": "Beasley"
    },
    "catcher": {
      "playerId": "21325139",
      "jaRegisteredName": "梅野　隆太郎",
      "teamCode": "T",
      "primaryNumber": "2",
      "primaryPosition": "Catcher",
      "jaStatus": "支配下選手",
      "batSide": "R",
      "pitchHand": "R",
      "height": "173",
      "weight": "79",
      "birthDate": "1991-06-17",
      "jaNotes": "",
      "notes": "",
      "jaBoxscoreName": "梅野",
      "boxscoreName": "Umeno",
      "jaFullName": "梅野　隆太郎",
      "jaFirstName": "隆太郎",
      "jaLastName": "梅野",
      "fullLFMName": "Umeno, Ryutaro",
      "firstName": "Ryutaro",
      "lastName": "Umeno"
    },
    "scoring": "StolenBase",
    "base": "2B",
    "pickoff": "",
    "inning": 5,
    "halfInning": "bottom",
    "outs": 2,
    "RoB": "1--",
    "runs": {
      "road": 6,
      "home": 1
    },
    "venue": {
      "jaBoxscoreName": "神宮",
      "boxscoreName": "Jingu",
      "jaName": "神宮",
      "name": "Jingu Stadium"
    },
    "teams": {
      "road": {
        "teamCode": "T",
        "teamName": "Tigers",
        "score": 6
      },
      "home": {
        "teamCode": "S",
        "teamName": "Swallows",
        "score": 3
      }
    },
    "jaText": "（走者・西川）二塁盗塁成功",
    "text": "Nishikawa steals 2nd base.",
    "url": "https://npb.jp/scores/2024/0808/s-t-16/playbyplay.html#com5-2",
    "catchers": [
      {
        "playerId": "21325139",
        "jaRegisteredName": "梅野　隆太郎",
        "teamCode": "T",
        "primaryNumber": "2",
        "primaryPosition": "Catcher",
        "jaStatus": "支配下選手",
        "batSide": "R",
        "pitchHand": "R",
        "height": "173",
        "weight": "79",
        "birthDate": "1991-06-17",
        "jaNotes": "",
        "notes": "",
        "jaBoxscoreName": "梅野",
        "boxscoreName": "Umeno",
        "jaFullName": "梅野　隆太郎",
        "jaFirstName": "隆太郎",
        "jaLastName": "梅野",
        "fullLFMName": "Umeno, Ryutaro",
        "firstName": "Ryutaro",
        "lastName": "Umeno"
      }
    ]
  },
  {
    "date": "2024-08-08",
    "runner": {
      "playerId": "61165132",
      "jaRegisteredName": "阿部　寿樹",
      "teamCode": "E",
      "primaryNumber": "4",
      "primaryPosition": "Infielder",
      "jaStatus": "支配下選手",
      "batSide": "R",
      "pitchHand": "R",
      "height": "185",
      "weight": "85",
      "birthDate": "1989-12-03",
      "jaNotes": "",
      "notes": "",
      "jaBoxscoreName": "阿部",
      "boxscoreName": "Abe",
      "jaFullName": "阿部　寿樹",
      "jaFirstName": "寿樹",
      "jaLastName": "阿部",
      "fullLFMName": "Abe, Toshiki",
      "firstName": "Toshiki",
      "lastName": "Abe"
    },
    "batter": {
      "playerId": "71375138",
      "jaRegisteredName": "太田　光",
      "teamCode": "E",
      "primaryNumber": "2",
      "primaryPosition": "Catcher",
      "jaStatus": "支配下選手",
      "batSide": "R",
      "pitchHand": "R",
      "height": "178",
      "weight": "76",
      "birthDate": "1996-10-14",
      "jaNotes": "",
      "notes": "",
      "jaBoxscoreName": "太田",
      "boxscoreName": "Ohta",
      "jaFullName": "太田　光",
      "jaFirstName": "光",
      "jaLastName": "太田",
      "fullLFMName": "Ohta, Hikaru",
      "firstName": "Hikaru",
      "lastName": "Ohta"
    },
    "pitcher": {
      "playerId": "41545132",
      "jaRegisteredName": "加藤　貴之",
      "teamCode": "F",
      "primaryNumber": "14",
      "primaryPosition": "Pitcher",
      "jaStatus": "支配下選手",
      "batSide": "L",
      "pitchHand": "L",
      "height": "182",
      "weight": "90",
      "birthDate": "1992-06-03",
      "jaNotes": "",
      "notes": "",
      "jaBoxscoreName": "加藤貴",
      "boxscoreName": "T.Katoh",
      "jaFullName": "加藤　貴之",
      "jaFirstName": "貴之",
      "jaLastName": "加藤",
      "fullLFMName": "Katoh, Takayuki",
      "firstName": "Takayuki",
      "lastName": "Katoh"
    },
    "catcher": {},
    "scoring": "CaughtStealing",
    "base": "2B",
    "pickoff": "",
    "inning": 4,
    "halfInning": "bottom",
    "outs": 1,
    "RoB": "1--",
    "runs": {
      "road": 4,
      "home": 3
    },
    "venue": {
      "jaBoxscoreName": "楽天モバイル",
      "boxscoreName": "Rakuten Mobile",
      "jaName": "楽天モバイルパーク宮城",
      "name": "Rakuten Mobile Park Miyagi"
    },
    "teams": {
      "road": {
        "teamCode": "F",
        "teamName": "Fighters",
        "score": 5
      },
      "home": {
        "teamCode": "E",
        "teamName": "Eagles",
        "score": 4
      }
    },
    "jaText": "（走者・阿部）二塁盗塁失敗",
    "text": "Abe caught stealing 2nd base.",
    "url": "https://npb.jp/scores/2024/0808/e-f-16/playbyplay.html#com4-2",
    "catchers": [
      {
        "playerId": "51055138",
        "jaRegisteredName": "田宮　裕涼",
        "teamCode": "F",
        "primaryNumber": "64",
        "primaryPosition": "Catcher",
        "jaStatus": "支配下選手",
        "batSide": "L",
        "pitchHand": "R",
        "height": "175",
        "weight": "79",
        "birthDate": "2000-06-13",
        "jaNotes": "",
        "notes": "",
        "jaBoxscoreName": "田宮",
        "boxscoreName": "Tamiya",
        "jaFullName": "田宮　裕涼",
        "jaFirstName": "裕涼",
        "jaLastName": "田宮",
        "fullLFMName": "Tamiya, Yua",
        "firstName": "Yua",
        "lastName": "Tamiya"
      },
      {
        "playerId": "61065137",
        "jaRegisteredName": "伏見　寅威",
        "teamCode": "F",
        "primaryNumber": "23",
        "primaryPosition": "Catcher",
        "jaStatus": "支配下選手",
        "batSide": "R",
        "pitchHand": "R",
        "height": "182",
        "weight": "87",
        "birthDate": "1990-05-12",
        "jaNotes": "",
        "notes": "",
        "jaBoxscoreName": "伏見",
        "boxscoreName": "Fushimi",
        "jaFullName": "伏見　寅威",
        "jaFirstName": "寅威",
        "jaLastName": "伏見",
        "fullLFMName": "Fushimi, Torai",
        "firstName": "Torai",
        "lastName": "Fushimi"
      }
    ]
  },
  {
    "date": "2024-08-08",
    "runner": {
      "playerId": "61965151",
      "jaRegisteredName": "小深田　大翔",
      "teamCode": "E",
      "primaryNumber": "0",
      "primaryPosition": "Infielder",
      "jaStatus": "支配下選手",
      "batSide": "L",
      "pitchHand": "R",
      "height": "168",
      "weight": "69",
      "birthDate": "1995-09-28",
      "jaNotes": "",
      "notes": "",
      "jaBoxscoreName": "小深田",
      "boxscoreName": "Kobukata",
      "jaFullName": "小深田　大翔",
      "jaFirstName": "大翔",
      "jaLastName": "小深田",
      "fullLFMName": "Kobukata, Hiroto",
      "firstName": "Hiroto",
      "lastName": "Kobukata"
    },
    "batter": {
      "playerId": "11015138",
      "jaRegisteredName": "辰己　涼介",
      "teamCode": "E",
      "primaryNumber": "8",
      "primaryPosition": "Outfielder",
      "jaStatus": "支配下選手",
      "batSide": "L",
      "pitchHand": "R",
      "height": "180",
      "weight": "74",
      "birthDate": "1996-12-27",
      "jaNotes": "",
      "notes": "",
      "jaBoxscoreName": "辰己",
      "boxscoreName": "R.Tatsumi",
      "jaFullName": "辰己　涼介",
      "jaFirstName": "涼介",
      "jaLastName": "辰己",
      "fullLFMName": "Tatsumi, Ryosuke",
      "firstName": "Ryosuke",
      "lastName": "Tatsumi"
    },
    "pitcher": {
      "playerId": "41545132",
      "jaRegisteredName": "加藤　貴之",
      "teamCode": "F",
      "primaryNumber": "14",
      "primaryPosition": "Pitcher",
      "jaStatus": "支配下選手",
      "batSide": "L",
      "pitchHand": "L",
      "height": "182",
      "weight": "90",
      "birthDate": "1992-06-03",
      "jaNotes": "",
      "notes": "",
      "jaBoxscoreName": "加藤貴",
      "boxscoreName": "T.Katoh",
      "jaFullName": "加藤　貴之",
      "jaFirstName": "貴之",
      "jaLastName": "加藤",
      "fullLFMName": "Katoh, Takayuki",
      "firstName": "Takayuki",
      "lastName": "Katoh"
    },
    "catcher": {},
    "scoring": "StolenBase",
    "base": "2B",
    "pickoff": "",
    "inning": 5,
    "halfInning": "bottom",
    "outs": 1,
    "RoB": "1--",
    "runs": {
      "road": 5,
      "home": 3
    },
    "venue": {
      "jaBoxscoreName": "楽天モバイル",
      "boxscoreName": "Rakuten Mobile",
      "jaName": "楽天モバイルパーク宮城",
      "name": "Rakuten Mobile Park Miyagi"
    },
    "teams": {
      "road": {
        "teamCode": "F",
        "teamName": "Fighters",
        "score": 5
      },
      "home": {
        "teamCode": "E",
        "teamName": "Eagles",
        "score": 4
      }
    },
    "jaText": "（走者・小深田）二塁盗塁成功",
    "text": "Kobukata steals 2nd base.",
    "url": "https://npb.jp/scores/2024/0808/e-f-16/playbyplay.html#com5-2",
    "catchers": [
      {
        "playerId": "51055138",
        "jaRegisteredName": "田宮　裕涼",
        "teamCode": "F",
        "primaryNumber": "64",
        "primaryPosition": "Catcher",
        "jaStatus": "支配下選手",
        "batSide": "L",
        "pitchHand": "R",
        "height": "175",
        "weight": "79",
        "birthDate": "2000-06-13",
        "jaNotes": "",
        "notes": "",
        "jaBoxscoreName": "田宮",
        "boxscoreName": "Tamiya",
        "jaFullName": "田宮　裕涼",
        "jaFirstName": "裕涼",
        "jaLastName": "田宮",
        "fullLFMName": "Tamiya, Yua",
        "firstName": "Yua",
        "lastName": "Tamiya"
      },
      {
        "playerId": "61065137",
        "jaRegisteredName": "伏見　寅威",
        "teamCode": "F",
        "primaryNumber": "23",
        "primaryPosition": "Catcher",
        "jaStatus": "支配下選手",
        "batSide": "R",
        "pitchHand": "R",
        "height": "182",
        "weight": "87",
        "birthDate": "1990-05-12",
        "jaNotes": "",
        "notes": "",
        "jaBoxscoreName": "伏見",
        "boxscoreName": "Fushimi",
        "jaFullName": "伏見　寅威",
        "jaFirstName": "寅威",
        "jaLastName": "伏見",
        "fullLFMName": "Fushimi, Torai",
        "firstName": "Torai",
        "lastName": "Fushimi"
      }
    ]
  },
  {
    "date": "2024-08-08",
    "runner": {
      "playerId": "81385138",
      "jaRegisteredName": "小郷　裕哉",
      "teamCode": "E",
      "primaryNumber": "51",
      "primaryPosition": "Outfielder",
      "jaStatus": "支配下選手",
      "batSide": "L",
      "pitchHand": "R",
      "height": "178",
      "weight": "85",
      "birthDate": "1996-08-03",
      "jaNotes": "",
      "notes": "",
      "jaBoxscoreName": "小郷",
      "boxscoreName": "Ogoh",
      "jaFullName": "小郷　裕哉",
      "jaFirstName": "裕哉",
      "jaLastName": "小郷",
      "fullLFMName": "Ogoh, Yuya",
      "firstName": "Yuya",
      "lastName": "Ogoh"
    },
    "batter": {
      "playerId": "61165132",
      "jaRegisteredName": "阿部　寿樹",
      "teamCode": "E",
      "primaryNumber": "4",
      "primaryPosition": "Infielder",
      "jaStatus": "支配下選手",
      "batSide": "R",
      "pitchHand": "R",
      "height": "185",
      "weight": "85",
      "birthDate": "1989-12-03",
      "jaNotes": "",
      "notes": "",
      "jaBoxscoreName": "阿部",
      "boxscoreName": "Abe",
      "jaFullName": "阿部　寿樹",
      "jaFirstName": "寿樹",
      "jaLastName": "阿部",
      "fullLFMName": "Abe, Toshiki",
      "firstName": "Toshiki",
      "lastName": "Abe"
    },
    "pitcher": {
      "playerId": "33135155",
      "jaRegisteredName": "松浦　慶斗",
      "teamCode": "F",
      "primaryNumber": "55",
      "primaryPosition": "Pitcher",
      "jaStatus": "支配下選手",
      "batSide": "L",
      "pitchHand": "L",
      "height": "186",
      "weight": "101",
      "birthDate": "2003-07-01",
      "jaNotes": "",
      "notes": "",
      "jaBoxscoreName": "松浦",
      "boxscoreName": "Matsuura",
      "jaFullName": "松浦　慶斗",
      "jaFirstName": "慶斗",
      "jaLastName": "松浦",
      "fullLFMName": "Matsuura, Keito",
      "firstName": "Keito",
      "lastName": "Matsuura"
    },
    "catcher": {},
    "scoring": "StolenBase",
    "base": "2B",
    "pickoff": "",
    "inning": 6,
    "halfInning": "bottom",
    "outs": 1,
    "RoB": "1--",
    "runs": {
      "road": 5,
      "home": 4
    },
    "venue": {
      "jaBoxscoreName": "楽天モバイル",
      "boxscoreName": "Rakuten Mobile",
      "jaName": "楽天モバイルパーク宮城",
      "name": "Rakuten Mobile Park Miyagi"
    },
    "teams": {
      "road": {
        "teamCode": "F",
        "teamName": "Fighters",
        "score": 5
      },
      "home": {
        "teamCode": "E",
        "teamName": "Eagles",
        "score": 4
      }
    },
    "jaText": "（走者・小郷）二塁盗塁成功",
    "text": "Ogoh steals 2nd base.",
    "url": "https://npb.jp/scores/2024/0808/e-f-16/playbyplay.html#com6-2",
    "catchers": [
      {
        "playerId": "51055138",
        "jaRegisteredName": "田宮　裕涼",
        "teamCode": "F",
        "primaryNumber": "64",
        "primaryPosition": "Catcher",
        "jaStatus": "支配下選手",
        "batSide": "L",
        "pitchHand": "R",
        "height": "175",
        "weight": "79",
        "birthDate": "2000-06-13",
        "jaNotes": "",
        "notes": "",
        "jaBoxscoreName": "田宮",
        "boxscoreName": "Tamiya",
        "jaFullName": "田宮　裕涼",
        "jaFirstName": "裕涼",
        "jaLastName": "田宮",
        "fullLFMName": "Tamiya, Yua",
        "firstName": "Yua",
        "lastName": "Tamiya"
      },
      {
        "playerId": "61065137",
        "jaRegisteredName": "伏見　寅威",
        "teamCode": "F",
        "primaryNumber": "23",
        "primaryPosition": "Catcher",
        "jaStatus": "支配下選手",
        "batSide": "R",
        "pitchHand": "R",
        "height": "182",
        "weight": "87",
        "birthDate": "1990-05-12",
        "jaNotes": "",
        "notes": "",
        "jaBoxscoreName": "伏見",
        "boxscoreName": "Fushimi",
        "jaFullName": "伏見　寅威",
        "jaFirstName": "寅威",
        "jaLastName": "伏見",
        "fullLFMName": "Fushimi, Torai",
        "firstName": "Torai",
        "lastName": "Fushimi"
      }
    ]
  },
  {
    "date": "2024-08-08",
    "runner": {
      "playerId": "11515139",
      "jaRegisteredName": "岡　大海",
      "teamCode": "M",
      "primaryNumber": "25",
      "primaryPosition": "Outfielder",
      "jaStatus": "支配下選手",
      "batSide": "R",
      "pitchHand": "R",
      "height": "185",
      "weight": "80",
      "birthDate": "1991-07-15",
      "jaNotes": "",
      "notes": "",
      "jaBoxscoreName": "岡",
      "boxscoreName": "Oka",
      "jaFullName": "岡　大海",
      "jaFirstName": "大海",
      "jaLastName": "岡",
      "fullLFMName": "Oka, Hiromi",
      "firstName": "Hiromi",
      "lastName": "Oka"
    },
    "batter": {
      "playerId": "63065155",
      "jaRegisteredName": "Ｇ．ポランコ",
      "teamCode": "M",
      "primaryNumber": "22",
      "primaryPosition": "Outfielder",
      "jaStatus": "支配下選手",
      "batSide": "L",
      "pitchHand": "L",
      "height": "196",
      "weight": "108",
      "birthDate": "1991-09-14",
      "jaNotes": "2/27 支配下選手登録",
      "notes": "Registered (Feb. 27).",
      "jaBoxscoreName": "ポランコ",
      "boxscoreName": "Polanco",
      "jaFullName": "グレゴリー・ポランコ",
      "jaFirstName": "グレゴリー",
      "jaLastName": "ポランコ",
      "fullLFMName": "Polanco, Gregory",
      "firstName": "Gregory",
      "lastName": "Polanco"
    },
    "pitcher": {
      "playerId": "61165139",
      "jaRegisteredName": "石川　柊太",
      "teamCode": "H",
      "primaryNumber": "29",
      "primaryPosition": "Pitcher",
      "jaStatus": "支配下選手",
      "batSide": "R",
      "pitchHand": "R",
      "height": "185",
      "weight": "88",
      "birthDate": "1991-12-27",
      "jaNotes": "",
      "notes": "",
      "jaBoxscoreName": "石川",
      "boxscoreName": "Ishikawa",
      "jaFullName": "石川　柊太",
      "jaFirstName": "柊太",
      "jaLastName": "石川",
      "fullLFMName": "Ishikawa, Shuta",
      "firstName": "Shuta",
      "lastName": "Ishikawa"
    },
    "catcher": {
      "playerId": "91595133",
      "jaRegisteredName": "甲斐　拓也",
      "teamCode": "H",
      "primaryNumber": "19",
      "primaryPosition": "Catcher",
      "jaStatus": "支配下選手",
      "batSide": "R",
      "pitchHand": "R",
      "height": "170",
      "weight": "87",
      "birthDate": "1992-11-05",
      "jaNotes": "",
      "notes": "",
      "jaBoxscoreName": "甲斐",
      "boxscoreName": "T.Kai",
      "jaFullName": "甲斐　拓也",
      "jaFirstName": "拓也",
      "jaLastName": "甲斐",
      "fullLFMName": "Kai, Takuya",
      "firstName": "Takuya",
      "lastName": "Kai"
    },
    "scoring": "StolenBase",
    "base": "2B",
    "pickoff": "",
    "inning": 1,
    "halfInning": "bottom",
    "outs": 1,
    "RoB": "1--",
    "runs": {
      "road": 0,
      "home": 0
    },
    "venue": {
      "jaBoxscoreName": "ZOZOマリン",
      "boxscoreName": "ZOZO Marine",
      "jaName": "ZOZOマリンスタジアム",
      "name": "ZOZO Marine Stadium"
    },
    "teams": {
      "road": {
        "teamCode": "H",
        "teamName": "Hawks",
        "score": 6
      },
      "home": {
        "teamCode": "M",
        "teamName": "Marines",
        "score": 3
      }
    },
    "jaText": "（走者・岡）二塁盗塁成功",
    "text": "Oka steals 2nd base.",
    "url": "https://npb.jp/scores/2024/0808/m-h-18/playbyplay.html#com1-2",
    "catchers": [
      {
        "playerId": "91595133",
        "jaRegisteredName": "甲斐　拓也",
        "teamCode": "H",
        "primaryNumber": "19",
        "primaryPosition": "Catcher",
        "jaStatus": "支配下選手",
        "batSide": "R",
        "pitchHand": "R",
        "height": "170",
        "weight": "87",
        "birthDate": "1992-11-05",
        "jaNotes": "",
        "notes": "",
        "jaBoxscoreName": "甲斐",
        "boxscoreName": "T.Kai",
        "jaFullName": "甲斐　拓也",
        "jaFirstName": "拓也",
        "jaLastName": "甲斐",
        "fullLFMName": "Kai, Takuya",
        "firstName": "Takuya",
        "lastName": "Kai"
      }
    ]
  },
  {
    "date": "2024-08-08",
    "runner": {
      "playerId": "41745135",
      "jaRegisteredName": "近藤　健介",
      "teamCode": "H",
      "primaryNumber": "3",
      "primaryPosition": "Outfielder",
      "jaStatus": "支配下選手",
      "batSide": "L",
      "pitchHand": "R",
      "height": "171",
      "weight": "86",
      "birthDate": "1993-08-09",
      "jaNotes": "",
      "notes": "",
      "jaBoxscoreName": "近藤",
      "boxscoreName": "Kondoh",
      "jaFullName": "近藤　健介",
      "jaFirstName": "健介",
      "jaLastName": "近藤",
      "fullLFMName": "Kondoh, Kensuke",
      "firstName": "Kensuke",
      "lastName": "Kondoh"
    },
    "batter": {
      "playerId": "81885155",
      "jaRegisteredName": "正木　智也",
      "teamCode": "H",
      "primaryNumber": "31",
      "primaryPosition": "Outfielder",
      "jaStatus": "支配下選手",
      "batSide": "R",
      "pitchHand": "R",
      "height": "182",
      "weight": "92",
      "birthDate": "1999-11-05",
      "jaNotes": "",
      "notes": "",
      "jaBoxscoreName": "正木",
      "boxscoreName": "Masaki",
      "jaFullName": "正木　智也",
      "jaFirstName": "智也",
      "jaLastName": "正木",
      "fullLFMName": "Masaki, Tomoya",
      "firstName": "Tomoya",
      "lastName": "Masaki"
    },
    "pitcher": {
      "playerId": "31035151",
      "jaRegisteredName": "佐々木　朗希",
      "teamCode": "M",
      "primaryNumber": "17",
      "primaryPosition": "Pitcher",
      "jaStatus": "支配下選手",
      "batSide": "R",
      "pitchHand": "R",
      "height": "192",
      "weight": "92",
      "birthDate": "2001-11-03",
      "jaNotes": "",
      "notes": "",
      "jaBoxscoreName": "佐々木",
      "boxscoreName": "Sasaki",
      "jaFullName": "佐々木　朗希",
      "jaFirstName": "朗希",
      "jaLastName": "佐々木",
      "fullLFMName": "Sasaki, Roki",
      "firstName": "Roki",
      "lastName": "Sasaki"
    },
    "catcher": {
      "playerId": "71075151",
      "jaRegisteredName": "佐藤　都志也",
      "teamCode": "M",
      "primaryNumber": "32",
      "primaryPosition": "Catcher",
      "jaStatus": "支配下選手",
      "batSide": "L",
      "pitchHand": "R",
      "height": "181",
      "weight": "86",
      "birthDate": "1998-01-27",
      "jaNotes": "",
      "notes": "",
      "jaBoxscoreName": "佐藤",
      "boxscoreName": "Satoh",
      "jaFullName": "佐藤　都志也",
      "jaFirstName": "都志也",
      "jaLastName": "佐藤",
      "fullLFMName": "Satoh, Toshiya",
      "firstName": "Toshiya",
      "lastName": "Satoh"
    },
    "scoring": "StolenBase",
    "base": "2B",
    "pickoff": "",
    "inning": 3,
    "halfInning": "top",
    "outs": 2,
    "RoB": "1--",
    "runs": {
      "road": 2,
      "home": 0
    },
    "venue": {
      "jaBoxscoreName": "ZOZOマリン",
      "boxscoreName": "ZOZO Marine",
      "jaName": "ZOZOマリンスタジアム",
      "name": "ZOZO Marine Stadium"
    },
    "teams": {
      "road": {
        "teamCode": "H",
        "teamName": "Hawks",
        "score": 6
      },
      "home": {
        "teamCode": "M",
        "teamName": "Marines",
        "score": 3
      }
    },
    "jaText": "（走者・近藤）二塁盗塁成功",
    "text": "Kondoh steals 2nd base.",
    "url": "https://npb.jp/scores/2024/0808/m-h-18/playbyplay.html#com3-1",
    "catchers": [
      {
        "playerId": "71075151",
        "jaRegisteredName": "佐藤　都志也",
        "teamCode": "M",
        "primaryNumber": "32",
        "primaryPosition": "Catcher",
        "jaStatus": "支配下選手",
        "batSide": "L",
        "pitchHand": "R",
        "height": "181",
        "weight": "86",
        "birthDate": "1998-01-27",
        "jaNotes": "",
        "notes": "",
        "jaBoxscoreName": "佐藤",
        "boxscoreName": "Satoh",
        "jaFullName": "佐藤　都志也",
        "jaFirstName": "都志也",
        "jaLastName": "佐藤",
        "fullLFMName": "Satoh, Toshiya",
        "firstName": "Toshiya",
        "lastName": "Satoh"
      }
    ]
  },
  {
    "date": "2024-08-08",
    "runner": {
      "playerId": "33335136",
      "jaRegisteredName": "和田　康士朗",
      "teamCode": "M",
      "primaryNumber": "63",
      "primaryPosition": "Outfielder",
      "jaStatus": "支配下選手",
      "batSide": "L",
      "pitchHand": "L",
      "height": "185",
      "weight": "77",
      "birthDate": "1999-01-14",
      "jaNotes": "",
      "notes": "",
      "jaBoxscoreName": "和田",
      "boxscoreName": "Wada",
      "jaFullName": "和田　康士朗",
      "jaFirstName": "康士朗",
      "jaLastName": "和田",
      "fullLFMName": "Wada, Koshiro",
      "firstName": "Koshiro",
      "lastName": "Wada"
    },
    "batter": {
      "playerId": "41645136",
      "jaRegisteredName": "藤岡　裕大",
      "teamCode": "M",
      "primaryNumber": "7",
      "primaryPosition": "Infielder",
      "jaStatus": "支配下選手",
      "batSide": "L",
      "pitchHand": "R",
      "height": "178",
      "weight": "86",
      "birthDate": "1993-08-08",
      "jaNotes": "",
      "notes": "",
      "jaBoxscoreName": "藤岡",
      "boxscoreName": "Fujioka",
      "jaFullName": "藤岡　裕大",
      "jaFirstName": "裕大",
      "jaLastName": "藤岡",
      "fullLFMName": "Fujioka, Yudai",
      "firstName": "Yudai",
      "lastName": "Fujioka"
    },
    "pitcher": {
      "playerId": "33435157",
      "jaRegisteredName": "Ｄ．ヘルナンデス",
      "teamCode": "H",
      "primaryNumber": "63",
      "primaryPosition": "Pitcher",
      "jaStatus": "支配下選手",
      "batSide": "L",
      "pitchHand": "L",
      "height": "188",
      "weight": "115",
      "birthDate": "1996-12-17",
      "jaNotes": "",
      "notes": "",
      "jaBoxscoreName": "ヘルナンデス",
      "boxscoreName": "Hernandez",
      "jaFullName": "ダーウィンゾン・ヘルナンデス",
      "jaFirstName": "ダーウィンゾン",
      "jaLastName": "ヘルナンデス",
      "fullLFMName": "Hernandez, Darwinzon",
      "firstName": "Darwinzon",
      "lastName": "Hernandez"
    },
    "catcher": {
      "playerId": "91595133",
      "jaRegisteredName": "甲斐　拓也",
      "teamCode": "H",
      "primaryNumber": "19",
      "primaryPosition": "Catcher",
      "jaStatus": "支配下選手",
      "batSide": "R",
      "pitchHand": "R",
      "height": "170",
      "weight": "87",
      "birthDate": "1992-11-05",
      "jaNotes": "",
      "notes": "",
      "jaBoxscoreName": "甲斐",
      "boxscoreName": "T.Kai",
      "jaFullName": "甲斐　拓也",
      "jaFirstName": "拓也",
      "jaLastName": "甲斐",
      "fullLFMName": "Kai, Takuya",
      "firstName": "Takuya",
      "lastName": "Kai"
    },
    "scoring": "StolenBase",
    "base": "2B",
    "pickoff": "",
    "inning": 8,
    "halfInning": "bottom",
    "outs": 0,
    "RoB": "1--",
    "runs": {
      "road": 5,
      "home": 1
    },
    "venue": {
      "jaBoxscoreName": "ZOZOマリン",
      "boxscoreName": "ZOZO Marine",
      "jaName": "ZOZOマリンスタジアム",
      "name": "ZOZO Marine Stadium"
    },
    "teams": {
      "road": {
        "teamCode": "H",
        "teamName": "Hawks",
        "score": 6
      },
      "home": {
        "teamCode": "M",
        "teamName": "Marines",
        "score": 3
      }
    },
    "jaText": "（走者・和田）二塁盗塁成功",
    "text": "Wada steals 2nd base.",
    "url": "https://npb.jp/scores/2024/0808/m-h-18/playbyplay.html#com8-2",
    "catchers": [
      {
        "playerId": "91595133",
        "jaRegisteredName": "甲斐　拓也",
        "teamCode": "H",
        "primaryNumber": "19",
        "primaryPosition": "Catcher",
        "jaStatus": "支配下選手",
        "batSide": "R",
        "pitchHand": "R",
        "height": "170",
        "weight": "87",
        "birthDate": "1992-11-05",
        "jaNotes": "",
        "notes": "",
        "jaBoxscoreName": "甲斐",
        "boxscoreName": "T.Kai",
        "jaFullName": "甲斐　拓也",
        "jaFirstName": "拓也",
        "jaLastName": "甲斐",
        "fullLFMName": "Kai, Takuya",
        "firstName": "Takuya",
        "lastName": "Kai"
      }
    ]
  },
  {
    "date": "2024-08-08",
    "runner": {
      "playerId": "61665157",
      "jaRegisteredName": "蛭間　拓哉",
      "teamCode": "L",
      "primaryNumber": "9",
      "primaryPosition": "Outfielder",
      "jaStatus": "支配下選手",
      "batSide": "L",
      "pitchHand": "L",
      "height": "177",
      "weight": "87",
      "birthDate": "2000-09-08",
      "jaNotes": "",
      "notes": "",
      "jaBoxscoreName": "蛭間",
      "boxscoreName": "Hiruma",
      "jaFullName": "蛭間　拓哉",
      "jaFirstName": "拓哉",
      "jaLastName": "蛭間",
      "fullLFMName": "Hiruma, Takuya",
      "firstName": "Takuya",
      "lastName": "Hiruma"
    },
    "batter": {
      "playerId": "83385153",
      "jaRegisteredName": "山村　崇嘉",
      "teamCode": "L",
      "primaryNumber": "32",
      "primaryPosition": "Infielder",
      "jaStatus": "支配下選手",
      "batSide": "L",
      "pitchHand": "R",
      "height": "183",
      "weight": "86",
      "birthDate": "2002-09-28",
      "jaNotes": "",
      "notes": "",
      "jaBoxscoreName": "山村",
      "boxscoreName": "Yamamura",
      "jaFullName": "山村　崇嘉",
      "jaFirstName": "崇嘉",
      "jaLastName": "山村",
      "fullLFMName": "Yamamura, Takayoshi",
      "firstName": "Takayoshi",
      "lastName": "Yamamura"
    },
    "pitcher": {
      "playerId": "61065159",
      "jaRegisteredName": "髙島　泰都",
      "teamCode": "B",
      "primaryNumber": "96",
      "primaryPosition": "Pitcher",
      "jaStatus": "支配下選手",
      "batSide": "R",
      "pitchHand": "R",
      "height": "181",
      "weight": "80",
      "birthDate": "1999-12-03",
      "jaNotes": "",
      "notes": "",
      "jaBoxscoreName": "髙島",
      "boxscoreName": "Takashima",
      "jaFullName": "髙島　泰都",
      "jaFirstName": "泰都",
      "jaLastName": "髙島",
      "fullLFMName": "Takashima, Taito",
      "firstName": "Taito",
      "lastName": "Takashima"
    },
    "catcher": {
      "playerId": "91495139",
      "jaRegisteredName": "森　友哉",
      "teamCode": "B",
      "primaryNumber": "4",
      "primaryPosition": "Catcher",
      "jaStatus": "支配下選手",
      "batSide": "L",
      "pitchHand": "R",
      "height": "170",
      "weight": "85",
      "birthDate": "1995-08-08",
      "jaNotes": "",
      "notes": "",
      "jaBoxscoreName": "森",
      "boxscoreName": "Mori",
      "jaFullName": "森　友哉",
      "jaFirstName": "友哉",
      "jaLastName": "森",
      "fullLFMName": "Mori, Tomoya",
      "firstName": "Tomoya",
      "lastName": "Mori"
    },
    "scoring": "CaughtStealing",
    "base": "2B",
    "pickoff": "",
    "inning": 1,
    "halfInning": "top",
    "outs": 2,
    "RoB": "1--",
    "runs": {
      "road": 0,
      "home": 0
    },
    "venue": {
      "jaBoxscoreName": "京セラD大阪",
      "boxscoreName": "Kyocera Dome",
      "jaName": "京セラドーム大阪",
      "name": "Kyocera Dome Osaka"
    },
    "teams": {
      "road": {
        "teamCode": "L",
        "teamName": "Lions",
        "score": 0
      },
      "home": {
        "teamCode": "B",
        "teamName": "Buffaloes",
        "score": 3
      }
    },
    "jaText": "（走者・蛭間）二塁盗塁失敗",
    "text": "Hiruma caught stealing 2nd base.",
    "url": "https://npb.jp/scores/2024/0808/b-l-18/playbyplay.html#com1-1",
    "catchers": [
      {
        "playerId": "91495139",
        "jaRegisteredName": "森　友哉",
        "teamCode": "B",
        "primaryNumber": "4",
        "primaryPosition": "Catcher",
        "jaStatus": "支配下選手",
        "batSide": "L",
        "pitchHand": "R",
        "height": "170",
        "weight": "85",
        "birthDate": "1995-08-08",
        "jaNotes": "",
        "notes": "",
        "jaBoxscoreName": "森",
        "boxscoreName": "Mori",
        "jaFullName": "森　友哉",
        "jaFirstName": "友哉",
        "jaLastName": "森",
        "fullLFMName": "Mori, Tomoya",
        "firstName": "Tomoya",
        "lastName": "Mori"
      }
    ]
  },
  {
    "date": "2024-08-08",
    "runner": {
      "playerId": "51955153",
      "jaRegisteredName": "来田　涼斗",
      "teamCode": "B",
      "primaryNumber": "38",
      "primaryPosition": "Outfielder",
      "jaStatus": "支配下選手",
      "batSide": "L",
      "pitchHand": "R",
      "height": "182",
      "weight": "93",
      "birthDate": "2002-10-16",
      "jaNotes": "",
      "notes": "",
      "jaBoxscoreName": "来田",
      "boxscoreName": "Kita",
      "jaFullName": "来田　涼斗",
      "jaFirstName": "涼斗",
      "jaLastName": "来田",
      "fullLFMName": "Kita, Ryoto",
      "firstName": "Ryoto",
      "lastName": "Kita"
    },
    "batter": {
      "playerId": "91495139",
      "jaRegisteredName": "森　友哉",
      "teamCode": "B",
      "primaryNumber": "4",
      "primaryPosition": "Catcher",
      "jaStatus": "支配下選手",
      "batSide": "L",
      "pitchHand": "R",
      "height": "170",
      "weight": "85",
      "birthDate": "1995-08-08",
      "jaNotes": "",
      "notes": "",
      "jaBoxscoreName": "森",
      "boxscoreName": "Mori",
      "jaFullName": "森　友哉",
      "jaFirstName": "友哉",
      "jaLastName": "森",
      "fullLFMName": "Mori, Tomoya",
      "firstName": "Tomoya",
      "lastName": "Mori"
    },
    "pitcher": {
      "playerId": "51155157",
      "jaRegisteredName": "青山　美夏人",
      "teamCode": "L",
      "primaryNumber": "29",
      "primaryPosition": "Pitcher",
      "jaStatus": "支配下選手",
      "batSide": "R",
      "pitchHand": "R",
      "height": "183",
      "weight": "94",
      "birthDate": "2000-07-19",
      "jaNotes": "",
      "notes": "",
      "jaBoxscoreName": "青山",
      "boxscoreName": "Aoyama",
      "jaFullName": "青山　美夏人",
      "jaFirstName": "美夏人",
      "jaLastName": "青山",
      "fullLFMName": "Aoyama, Minato",
      "firstName": "Minato",
      "lastName": "Aoyama"
    },
    "catcher": {},
    "scoring": "StolenBase",
    "base": "2B",
    "pickoff": "",
    "inning": 1,
    "halfInning": "bottom",
    "outs": 2,
    "RoB": "1--",
    "runs": {
      "road": 0,
      "home": 0
    },
    "venue": {
      "jaBoxscoreName": "京セラD大阪",
      "boxscoreName": "Kyocera Dome",
      "jaName": "京セラドーム大阪",
      "name": "Kyocera Dome Osaka"
    },
    "teams": {
      "road": {
        "teamCode": "L",
        "teamName": "Lions",
        "score": 0
      },
      "home": {
        "teamCode": "B",
        "teamName": "Buffaloes",
        "score": 3
      }
    },
    "jaText": "（走者・来田）二塁盗塁成功",
    "text": "Kita steals 2nd base.",
    "url": "https://npb.jp/scores/2024/0808/b-l-18/playbyplay.html#com1-2",
    "catchers": [
      {
        "playerId": "81785155",
        "jaRegisteredName": "古賀　悠斗",
        "teamCode": "L",
        "primaryNumber": "22",
        "primaryPosition": "Catcher",
        "jaStatus": "支配下選手",
        "batSide": "R",
        "pitchHand": "R",
        "height": "174",
        "weight": "86",
        "birthDate": "1999-09-10",
        "jaNotes": "",
        "notes": "",
        "jaBoxscoreName": "古賀",
        "boxscoreName": "Koga",
        "jaFullName": "古賀　悠斗",
        "jaFirstName": "悠斗",
        "jaLastName": "古賀",
        "fullLFMName": "Koga, Yuto",
        "firstName": "Yuto",
        "lastName": "Koga"
      },
      {
        "playerId": "61265151",
        "jaRegisteredName": "柘植　世那",
        "teamCode": "L",
        "primaryNumber": "37",
        "primaryPosition": "Catcher",
        "jaStatus": "支配下選手",
        "batSide": "R",
        "pitchHand": "R",
        "height": "174",
        "weight": "88",
        "birthDate": "1997-06-03",
        "jaNotes": "",
        "notes": "",
        "jaBoxscoreName": "柘植",
        "boxscoreName": "Tsuge",
        "jaFullName": "柘植　世那",
        "jaFirstName": "世那",
        "jaLastName": "柘植",
        "fullLFMName": "Tsuge, Sena",
        "firstName": "Sena",
        "lastName": "Tsuge"
      }
    ]
  },
  {
    "date": "2024-08-08",
    "runner": {
      "playerId": "41245130",
      "jaRegisteredName": "外崎　修汰",
      "teamCode": "L",
      "primaryNumber": "5",
      "primaryPosition": "Infielder",
      "jaStatus": "支配下選手",
      "batSide": "R",
      "pitchHand": "R",
      "height": "177",
      "weight": "82",
      "birthDate": "1992-12-20",
      "jaNotes": "",
      "notes": "",
      "jaBoxscoreName": "外崎",
      "boxscoreName": "Tonosaki",
      "jaFullName": "外崎　修汰",
      "jaFirstName": "修汰",
      "jaLastName": "外崎",
      "fullLFMName": "Tonosaki, Shuta",
      "firstName": "Shuta",
      "lastName": "Tonosaki"
    },
    "batter": {
      "playerId": "83585159",
      "jaRegisteredName": "Ａ．ガルシア",
      "teamCode": "L",
      "primaryNumber": "78",
      "primaryPosition": "Outfielder",
      "jaStatus": "支配下選手",
      "batSide": "S",
      "pitchHand": "R",
      "height": "198",
      "weight": "115",
      "birthDate": "2000-09-05",
      "jaNotes": "",
      "notes": "",
      "jaBoxscoreName": "ガルシア",
      "boxscoreName": "Garcia",
      "jaFullName": "アンソニー・ガルシア",
      "jaFirstName": "アンソニー",
      "jaLastName": "ガルシア",
      "fullLFMName": "Garcia, Anthony",
      "firstName": "Anthony",
      "lastName": "Garcia"
    },
    "pitcher": {
      "playerId": "61065159",
      "jaRegisteredName": "髙島　泰都",
      "teamCode": "B",
      "primaryNumber": "96",
      "primaryPosition": "Pitcher",
      "jaStatus": "支配下選手",
      "batSide": "R",
      "pitchHand": "R",
      "height": "181",
      "weight": "80",
      "birthDate": "1999-12-03",
      "jaNotes": "",
      "notes": "",
      "jaBoxscoreName": "髙島",
      "boxscoreName": "Takashima",
      "jaFullName": "髙島　泰都",
      "jaFirstName": "泰都",
      "jaLastName": "髙島",
      "fullLFMName": "Takashima, Taito",
      "firstName": "Taito",
      "lastName": "Takashima"
    },
    "catcher": {
      "playerId": "91495139",
      "jaRegisteredName": "森　友哉",
      "teamCode": "B",
      "primaryNumber": "4",
      "primaryPosition": "Catcher",
      "jaStatus": "支配下選手",
      "batSide": "L",
      "pitchHand": "R",
      "height": "170",
      "weight": "85",
      "birthDate": "1995-08-08",
      "jaNotes": "",
      "notes": "",
      "jaBoxscoreName": "森",
      "boxscoreName": "Mori",
      "jaFullName": "森　友哉",
      "jaFirstName": "友哉",
      "jaLastName": "森",
      "fullLFMName": "Mori, Tomoya",
      "firstName": "Tomoya",
      "lastName": "Mori"
    },
    "scoring": "StolenBase",
    "base": "2B",
    "pickoff": "",
    "inning": 5,
    "halfInning": "top",
    "outs": 1,
    "RoB": "1--",
    "runs": {
      "road": 0,
      "home": 1
    },
    "venue": {
      "jaBoxscoreName": "京セラD大阪",
      "boxscoreName": "Kyocera Dome",
      "jaName": "京セラドーム大阪",
      "name": "Kyocera Dome Osaka"
    },
    "teams": {
      "road": {
        "teamCode": "L",
        "teamName": "Lions",
        "score": 0
      },
      "home": {
        "teamCode": "B",
        "teamName": "Buffaloes",
        "score": 3
      }
    },
    "jaText": "（走者・外崎）二塁盗塁成功",
    "text": "Tonosaki steals 2nd base.",
    "url": "https://npb.jp/scores/2024/0808/b-l-18/playbyplay.html#com5-1",
    "catchers": [
      {
        "playerId": "91495139",
        "jaRegisteredName": "森　友哉",
        "teamCode": "B",
        "primaryNumber": "4",
        "primaryPosition": "Catcher",
        "jaStatus": "支配下選手",
        "batSide": "L",
        "pitchHand": "R",
        "height": "170",
        "weight": "85",
        "birthDate": "1995-08-08",
        "jaNotes": "",
        "notes": "",
        "jaBoxscoreName": "森",
        "boxscoreName": "Mori",
        "jaFullName": "森　友哉",
        "jaFirstName": "友哉",
        "jaLastName": "森",
        "fullLFMName": "Mori, Tomoya",
        "firstName": "Tomoya",
        "lastName": "Mori"
      }
    ]
  },
  {
    "date": "2024-08-08",
    "runner": {
      "playerId": "91495130",
      "jaRegisteredName": "西野　真弘",
      "teamCode": "B",
      "primaryNumber": "5",
      "primaryPosition": "Infielder",
      "jaStatus": "支配下選手",
      "batSide": "L",
      "pitchHand": "R",
      "height": "167",
      "weight": "71",
      "birthDate": "1990-08-02",
      "jaNotes": "",
      "notes": "",
      "jaBoxscoreName": "西野",
      "boxscoreName": "Nishino",
      "jaFullName": "西野　真弘",
      "jaFirstName": "真弘",
      "jaLastName": "西野",
      "fullLFMName": "Nishino, Masahiro",
      "firstName": "Masahiro",
      "lastName": "Nishino"
    },
    "batter": {
      "playerId": "11815130",
      "jaRegisteredName": "宗　佑磨",
      "teamCode": "B",
      "primaryNumber": "6",
      "primaryPosition": "Infielder",
      "jaStatus": "支配下選手",
      "batSide": "L",
      "pitchHand": "R",
      "height": "181",
      "weight": "83",
      "birthDate": "1996-06-07",
      "jaNotes": "",
      "notes": "",
      "jaBoxscoreName": "宗",
      "boxscoreName": "Mune",
      "jaFullName": "宗　佑磨",
      "jaFirstName": "佑磨",
      "jaLastName": "宗",
      "fullLFMName": "Mune, Yuma",
      "firstName": "Yuma",
      "lastName": "Mune"
    },
    "pitcher": {
      "playerId": "53055159",
      "jaRegisteredName": "Ｊ．ヤン",
      "teamCode": "L",
      "primaryNumber": "00",
      "primaryPosition": "Pitcher",
      "jaStatus": "支配下選手",
      "batSide": "L",
      "pitchHand": "L",
      "height": "190",
      "weight": "83",
      "birthDate": "1996-08-17",
      "jaNotes": "",
      "notes": "",
      "jaBoxscoreName": "ヤン",
      "boxscoreName": "Yan",
      "jaFullName": "ジェフリー・ヤン",
      "jaFirstName": "ジェフリー",
      "jaLastName": "ヤン",
      "fullLFMName": "Yan, Jefry",
      "firstName": "Jefry",
      "lastName": "Yan"
    },
    "catcher": {},
    "scoring": "StolenBase",
    "base": "2B",
    "pickoff": "",
    "inning": 6,
    "halfInning": "bottom",
    "outs": 1,
    "RoB": "1--",
    "runs": {
      "road": 0,
      "home": 1
    },
    "venue": {
      "jaBoxscoreName": "京セラD大阪",
      "boxscoreName": "Kyocera Dome",
      "jaName": "京セラドーム大阪",
      "name": "Kyocera Dome Osaka"
    },
    "teams": {
      "road": {
        "teamCode": "L",
        "teamName": "Lions",
        "score": 0
      },
      "home": {
        "teamCode": "B",
        "teamName": "Buffaloes",
        "score": 3
      }
    },
    "jaText": "（走者・西野）二塁盗塁成功",
    "text": "Nishino steals 2nd base.",
    "url": "https://npb.jp/scores/2024/0808/b-l-18/playbyplay.html#com6-2",
    "catchers": [
      {
        "playerId": "81785155",
        "jaRegisteredName": "古賀　悠斗",
        "teamCode": "L",
        "primaryNumber": "22",
        "primaryPosition": "Catcher",
        "jaStatus": "支配下選手",
        "batSide": "R",
        "pitchHand": "R",
        "height": "174",
        "weight": "86",
        "birthDate": "1999-09-10",
        "jaNotes": "",
        "notes": "",
        "jaBoxscoreName": "古賀",
        "boxscoreName": "Koga",
        "jaFullName": "古賀　悠斗",
        "jaFirstName": "悠斗",
        "jaLastName": "古賀",
        "fullLFMName": "Koga, Yuto",
        "firstName": "Yuto",
        "lastName": "Koga"
      },
      {
        "playerId": "61265151",
        "jaRegisteredName": "柘植　世那",
        "teamCode": "L",
        "primaryNumber": "37",
        "primaryPosition": "Catcher",
        "jaStatus": "支配下選手",
        "batSide": "R",
        "pitchHand": "R",
        "height": "174",
        "weight": "88",
        "birthDate": "1997-06-03",
        "jaNotes": "",
        "notes": "",
        "jaBoxscoreName": "柘植",
        "boxscoreName": "Tsuge",
        "jaFullName": "柘植　世那",
        "jaFirstName": "世那",
        "jaLastName": "柘植",
        "fullLFMName": "Tsuge, Sena",
        "firstName": "Sena",
        "lastName": "Tsuge"
      }
    ]
  },
  {
    "date": "2024-08-08",
    "runner": {
      "playerId": "83385153",
      "jaRegisteredName": "山村　崇嘉",
      "teamCode": "L",
      "primaryNumber": "32",
      "primaryPosition": "Infielder",
      "jaStatus": "支配下選手",
      "batSide": "L",
      "pitchHand": "R",
      "height": "183",
      "weight": "86",
      "birthDate": "2002-09-28",
      "jaNotes": "",
      "notes": "",
      "jaBoxscoreName": "山村",
      "boxscoreName": "Yamamura",
      "jaFullName": "山村　崇嘉",
      "jaFirstName": "崇嘉",
      "jaLastName": "山村",
      "fullLFMName": "Yamamura, Takayoshi",
      "firstName": "Takayoshi",
      "lastName": "Yamamura"
    },
    "batter": {
      "playerId": "41245130",
      "jaRegisteredName": "外崎　修汰",
      "teamCode": "L",
      "primaryNumber": "5",
      "primaryPosition": "Infielder",
      "jaStatus": "支配下選手",
      "batSide": "R",
      "pitchHand": "R",
      "height": "177",
      "weight": "82",
      "birthDate": "1992-12-20",
      "jaNotes": "",
      "notes": "",
      "jaBoxscoreName": "外崎",
      "boxscoreName": "Tonosaki",
      "jaFullName": "外崎　修汰",
      "jaFirstName": "修汰",
      "jaLastName": "外崎",
      "fullLFMName": "Tonosaki, Shuta",
      "firstName": "Shuta",
      "lastName": "Tonosaki"
    },
    "pitcher": {
      "playerId": "61965136",
      "jaRegisteredName": "鈴木　博志",
      "teamCode": "B",
      "primaryNumber": "66",
      "primaryPosition": "Pitcher",
      "jaStatus": "支配下選手",
      "batSide": "R",
      "pitchHand": "R",
      "height": "182",
      "weight": "95",
      "birthDate": "1997-03-22",
      "jaNotes": "",
      "notes": "",
      "jaBoxscoreName": "鈴木",
      "boxscoreName": "Suzuki",
      "jaFullName": "鈴木　博志",
      "jaFirstName": "博志",
      "jaLastName": "鈴木",
      "fullLFMName": "Suzuki, Hiroshi",
      "firstName": "Hiroshi",
      "lastName": "Suzuki"
    },
    "catcher": {
      "playerId": "91495139",
      "jaRegisteredName": "森　友哉",
      "teamCode": "B",
      "primaryNumber": "4",
      "primaryPosition": "Catcher",
      "jaStatus": "支配下選手",
      "batSide": "L",
      "pitchHand": "R",
      "height": "170",
      "weight": "85",
      "birthDate": "1995-08-08",
      "jaNotes": "",
      "notes": "",
      "jaBoxscoreName": "森",
      "boxscoreName": "Mori",
      "jaFullName": "森　友哉",
      "jaFirstName": "友哉",
      "jaLastName": "森",
      "fullLFMName": "Mori, Tomoya",
      "firstName": "Tomoya",
      "lastName": "Mori"
    },
    "scoring": "StolenBase",
    "base": "2B",
    "pickoff": "",
    "inning": 7,
    "halfInning": "top",
    "outs": 1,
    "RoB": "1--",
    "runs": {
      "road": 0,
      "home": 1
    },
    "venue": {
      "jaBoxscoreName": "京セラD大阪",
      "boxscoreName": "Kyocera Dome",
      "jaName": "京セラドーム大阪",
      "name": "Kyocera Dome Osaka"
    },
    "teams": {
      "road": {
        "teamCode": "L",
        "teamName": "Lions",
        "score": 0
      },
      "home": {
        "teamCode": "B",
        "teamName": "Buffaloes",
        "score": 3
      }
    },
    "jaText": "（走者・山村）二塁盗塁成功",
    "text": "Yamamura steals 2nd base.",
    "url": "https://npb.jp/scores/2024/0808/b-l-18/playbyplay.html#com7-1",
    "catchers": [
      {
        "playerId": "91495139",
        "jaRegisteredName": "森　友哉",
        "teamCode": "B",
        "primaryNumber": "4",
        "primaryPosition": "Catcher",
        "jaStatus": "支配下選手",
        "batSide": "L",
        "pitchHand": "R",
        "height": "170",
        "weight": "85",
        "birthDate": "1995-08-08",
        "jaNotes": "",
        "notes": "",
        "jaBoxscoreName": "森",
        "boxscoreName": "Mori",
        "jaFullName": "森　友哉",
        "jaFirstName": "友哉",
        "jaLastName": "森",
        "fullLFMName": "Mori, Tomoya",
        "firstName": "Tomoya",
        "lastName": "Mori"
      }
    ]
  }
]